pkg_deploy/__init__.py
pkg_deploy/build.py
pkg_deploy/deploy.py
pkg_deploy/upload.py
pkg_deploy/utils.py
pkg_deploy/version_managment.py
pkg_deploy-1.0.12.dist-info/METADATA
pkg_deploy-1.0.12.dist-info/WHEEL
pkg_deploy-1.0.12.dist-info/entry_points.txt
pkg_deploy-1.0.12.dist-info/top_level.txt
pkg_deploy-1.0.12.dist-info/RECORD
