Metadata-Version: 2.4
Name: pkg-deploy
Version: 1.0.12
Summary: Modern Python Package Deployment Tool
Author-email: cw <cw.devworks@gmail.com>
License: Apache-2.0
Classifier: License :: OSI Approved :: Apache Software License
Classifier: Development Status :: 4 - Beta
Classifier: Intended Audience :: Developers
Classifier: Programming Language :: Python :: 3
Classifier: Programming Language :: Python :: 3.8
Classifier: Programming Language :: Python :: 3.9
Classifier: Programming Language :: Python :: 3.10
Classifier: Programming Language :: Python :: 3.11
Classifier: Programming Language :: Python :: 3.12
Classifier: Programming Language :: Python :: 3.13
Classifier: Topic :: Software Development :: Build Tools
Classifier: Topic :: System :: Software Distribution
Classifier: Operating System :: OS Independent
Requires-Python: >=3.8
Requires-Dist: toml
Requires-Dist: tomlkit
Requires-Dist: build
Requires-Dist: twine
Requires-Dist: Cython
Requires-Dist: setuptools>=70
Requires-Dist: cibuildwheel
